routes/__init__.py
routes/__main__.py
routes/commands/__init__.py
routes/commands/viz.py
routes/commands/which.py
routes/const.py
routes/main.py
routes/rules/__init__.py
routes/rules/angular.yml
routes/rules/cakephp.yml
routes/rules/chi.yml
routes/rules/django-rest-framework.yml
routes/rules/django.yml
routes/rules/express.yml
routes/rules/fastapi.yml
routes/rules/flask.yml
routes/rules/gin.yml
routes/rules/gorilla.yml
routes/rules/grape.yml
routes/rules/jax-rs.yml
routes/rules/laravel.yml
routes/rules/rails.yml
routes/rules/react.yml
routes/rules/sanic.yml
routes/rules/spring.yml
routes/rules/symfony.yml
routes/rules/test-route-detect.yml
routes/templates/__init__.py
routes/templates/routes.tmpl.html
routes/types.py
routes/util.py
route_detect-0.8.0.dist-info/LICENSE
route_detect-0.8.0.dist-info/METADATA
route_detect-0.8.0.dist-info/WHEEL
route_detect-0.8.0.dist-info/entry_points.txt
route_detect-0.8.0.dist-info/RECORD
