Metadata-Version: 2.1
Name: route-detect
Version: 0.8.0
Summary: Find authentication (authn) and authorization (authz) security bugs in web application routes.
Home-page: https://github.com/mschwager/route-detect
License: BSD-3-Clause
Requires-Python: >=3.8,<4.0
Classifier: License :: OSI Approved :: BSD License
Classifier: Programming Language :: Python :: 3
Classifier: Programming Language :: Python :: 3.8
Classifier: Programming Language :: Python :: 3.9
Classifier: Programming Language :: Python :: 3.10
Classifier: Programming Language :: Python :: 3.11
Classifier: Programming Language :: Python :: 3.12
Requires-Dist: semgrep (>=1.36.0,<2.0.0)
Project-URL: Repository, https://github.com/mschwager/route-detect
